airpiano.py
airpiano-0.0.8.dist-info/METADATA
airpiano-0.0.8.dist-info/WHEEL
airpiano-0.0.8.dist-info/entry_points.txt
airpiano-0.0.8.dist-info/top_level.txt
airpiano-0.0.8.dist-info/RECORD
